hyperdt/__init__.py
hyperdt/conversions.py
hyperdt/ensemble.py
hyperdt/hyperbolic_trig.py
hyperdt/toy_data.py
hyperdt/tree.py
hyperdt/visualization.py
hyperdt-0.0.3.dist-info/LICENSE
hyperdt-0.0.3.dist-info/METADATA
hyperdt-0.0.3.dist-info/WHEEL
hyperdt-0.0.3.dist-info/top_level.txt
hyperdt-0.0.3.dist-info/RECORD
