Metadata-Version: 2.1
Name: hyperdt
Version: 0.0.3
Summary: Fast Hyperboloid Decision Tree Algorithms
Home-page: http://www.github.com/pchlenski/hyperdt
Author: Philippe Chlenski
Author-email: pac@cs.columbia.edu
License-File: LICENSE
Requires-Dist: numpy
Requires-Dist: geomstats
Requires-Dist: matplotlib
Requires-Dist: scikit-learn
Requires-Dist: scipy
Requires-Dist: tqdm
Requires-Dist: joblib
